<?xml version="1.0" encoding="utf-8"?>
<FlightNodes>
  <Node name="地獄火半島，黑暗之門" continent="530" master="18931" x="-327.35" y="1020.49" z="54.25">
    <Connections>
      <Connection name="榮譽堡，地獄火半島" />
      <Connection name="特爾哈曼神廟，地獄火半島" />
      <Connection name="泰倫多爾，贊格沼澤" />
      <Connection name="泰拉，納葛蘭" />
      <Connection name="艾蘭里堡壘，泰洛卡森林" />
      <Connection name="52區，虛空風暴" />
      <Connection name="撒塔斯，泰洛卡森林" />
      <Connection name="破碎崗哨，地獄火半島" />
      <Connection name="奧雷伯爾港，贊格沼澤" />
    </Connections>
  </Node>
  <Node name="榮譽堡，地獄火半島" continent="530" x="-673.42" y="2717.27" z="94.18">
    <Connections>
      <Connection name="地獄火半島，黑暗之門" />
      <Connection name="撒塔斯，泰洛卡森林" />
    </Connections>
  </Node>
  <Node name="特爾哈曼神廟，地獄火半島" continent="530" x="199.16" y="4241.56" z="121.75">
    <Connections>
      <Connection name="地獄火半島，黑暗之門" />
      <Connection name="撒塔斯，泰洛卡森林" />
    </Connections>
  </Node>
  <Node name="泰倫多爾，贊格沼澤" continent="530" x="213.75" y="6063.75" z="148.31">
    <Connections>
      <Connection name="地獄火半島，黑暗之門" />
      <Connection name="撒塔斯，泰洛卡森林" />
    </Connections>
  </Node>
  <Node name="泰拉，納葛蘭" continent="530" x="-2729" y="7305.3" z="88.64">
    <Connections>
      <Connection name="地獄火半島，黑暗之門" />
      <Connection name="撒塔斯，泰洛卡森林" />
    </Connections>
  </Node>
  <Node name="艾蘭里堡壘，泰洛卡森林" continent="530" x="-2987.24" y="3872.78" z="9.13">
    <Connections>
      <Connection name="地獄火半島，黑暗之門" />
      <Connection name="撒塔斯，泰洛卡森林" />
    </Connections>
  </Node>
  <Node name="52區，虛空風暴" continent="530" x="3082.31" y="3596.11" z="144.02">
    <Connections>
      <Connection name="地獄火半島，黑暗之門" />
      <Connection name="撒塔斯，泰洛卡森林" />
    </Connections>
  </Node>
  <Node name="蠻錘要塞，影月谷" continent="530" x="-3982.07" y="2156.47" z="105.15">
    <Connections />
  </Node>
  <Node name="希爾瓦納，劍刃山脈" continent="530" x="2183.65" y="6794.46" z="183.28">
    <Connections />
  </Node>
  <Node name="撒塔斯，泰洛卡森林" continent="530" master="18940" x="-1837.23" y="5301.9" z="-12.43">
    <Connections>
      <Connection name="地獄火半島，黑暗之門" />
      <Connection name="榮譽堡，地獄火半島" />
      <Connection name="特爾哈曼神廟，地獄火半島" />
      <Connection name="泰倫多爾，贊格沼澤" />
      <Connection name="泰拉，納葛蘭" />
      <Connection name="艾蘭里堡壘，泰洛卡森林" />
      <Connection name="52區，虛空風暴" />
      <Connection name="破碎崗哨，地獄火半島" />
      <Connection name="奧雷伯爾港，贊格沼澤" />
    </Connections>
  </Node>
  <Node name="風暴之尖，虛空風暴" continent="530" x="4157.58" y="2959.69" z="352.08">
    <Connections />
  </Node>
  <Node name="破碎崗哨，地獄火半島" continent="530" x="276.2" y="1486.91" z="-15.1">
    <Connections>
      <Connection name="地獄火半島，黑暗之門" />
      <Connection name="撒塔斯，泰洛卡森林" />
    </Connections>
  </Node>
  <Node name="扭曲太空，虛空風暴" continent="530" x="2974.95" y="1848.24" z="141.28">
    <Connections />
  </Node>
  <Node name="托斯利基地，劍刃山脈" continent="530" x="1857.35" y="5531.87" z="277.01">
    <Connections />
  </Node>
  <Node name="永恆樹林，劍刃山脈" continent="530" x="2976.01" y="5501.13" z="143.67">
    <Connections />
  </Node>
  <Node name="奧雷伯爾港，贊格沼澤" continent="530" x="966.67" y="7399.16" z="29.14">
    <Connections>
      <Connection name="地獄火半島，黑暗之門" />
      <Connection name="撒塔斯，泰洛卡森林" />
    </Connections>
  </Node>
  <Node name="諾達希爾，海加爾" continent="1" master="41861" x="5584.06" y="-3569.84" z="1570.6">
    <Connections>
      <Connection name="洛丹諾，黑海岸" />
      <Connection name="魯瑟蘭村，泰達希爾" />
      <Connection name="塞拉摩，塵泥沼澤" />
      <Connection name="加基森，塔納利斯" />
      <Connection name="月光林地" />
      <Connection name="塞納里奧城堡，希利蘇斯" />
      <Connection name="馬紹爾觀測站，安戈洛環形山" />
      <Connection name="棘齒城，北貧瘠之地" />
      <Connection name="血色守望，血謎島" />
      <Connection name="艾克索達" />
      <Connection name="泥鏈營地，塵泥沼澤" />
      <Connection name="古樹之林，黑海岸" />
      <Connection name="苔蘚堆，安戈洛環形山" />
      <Connection name="北方城堡，南貧瘠之地" />
      <Connection name="多蘭納爾，泰達希爾" />
      <Connection name="達納蘇斯，泰達希爾" />
      <Connection name="菲茲爾與普茲克的高速駁船，千針石林" />
      <Connection name="藍色守望，藍謎島" />
      <Connection name="艾森娜之林，海加爾" />
      <Connection name="艾維娜聖壇，海加爾" />
      <Connection name="蘭姆卡韓，奧丹姆" />
    </Connections>
  </Node>
  <Node name="洛丹諾，黑海岸" continent="1" x="7459.9" y="-326.56" z="8.09">
    <Connections>
      <Connection name="諾達希爾，海加爾" />
      <Connection name="艾森娜之林，海加爾" />
      <Connection name="艾維娜聖壇，海加爾" />
      <Connection name="蘭姆卡韓，奧丹姆" />
    </Connections>
  </Node>
  <Node name="魯瑟蘭村，泰達希爾" continent="1" x="8383.75" y="980.964" z="30.8292">
    <Connections>
      <Connection name="諾達希爾，海加爾" />
      <Connection name="艾森娜之林，海加爾" />
      <Connection name="艾維娜聖壇，海加爾" />
      <Connection name="蘭姆卡韓，奧丹姆" />
    </Connections>
  </Node>
  <Node name="阿斯特蘭納，梣谷" continent="1" x="2827.34" y="-289.24" z="107.16">
    <Connections />
  </Node>
  <Node name="蔭枝林，菲拉斯" continent="1" x="-4996.88" y="73.9427" z="99.8385">
    <Connections />
  </Node>
  <Node name="塞拉摩，塵泥沼澤" continent="1" x="-3825.37" y="-4516.58" z="10.44">
    <Connections>
      <Connection name="諾達希爾，海加爾" />
      <Connection name="艾森娜之林，海加爾" />
      <Connection name="艾維娜聖壇，海加爾" />
      <Connection name="蘭姆卡韓，奧丹姆" />
    </Connections>
  </Node>
  <Node name="薩歐達拉瞰臺，石爪山脈" continent="1" x="2147.25" y="1537.87" z="341.24">
    <Connections />
  </Node>
  <Node name="尼耶爾前哨站，淒涼之地" continent="1" x="139.24" y="1325.82" z="193.5">
    <Connections />
  </Node>
  <Node name="加基森，塔納利斯" continent="1" x="-7185.97" y="-3768.24" z="9.30053">
    <Connections>
      <Connection name="諾達希爾，海加爾" />
      <Connection name="艾森娜之林，海加爾" />
      <Connection name="艾維娜聖壇，海加爾" />
      <Connection name="蘭姆卡韓，奧丹姆" />
    </Connections>
  </Node>
  <Node name="羽月要塞，菲拉斯" continent="1" x="-4467.04" y="2188.64" z="17.8939">
    <Connections />
  </Node>
  <Node name="月光林地" continent="1" x="7458.45" y="-2487.21" z="462.33">
    <Connections>
      <Connection name="諾達希爾，海加爾" />
      <Connection name="艾森娜之林，海加爾" />
      <Connection name="艾維娜聖壇，海加爾" />
      <Connection name="蘭姆卡韓，奧丹姆" />
    </Connections>
  </Node>
  <Node name="永望鎮，冬泉谷" continent="1" x="6796.8" y="-4742.39" z="701.5">
    <Connections />
  </Node>
  <Node name="刺枝林地，費伍德森林" continent="1" x="6214.32" y="-1874.28" z="565.956">
    <Connections />
  </Node>
  <Node name="塞納里奧城堡，希利蘇斯" continent="1" x="-6761.83" y="772.03" z="88.91">
    <Connections>
      <Connection name="諾達希爾，海加爾" />
      <Connection name="艾森娜之林，海加爾" />
      <Connection name="艾維娜聖壇，海加爾" />
      <Connection name="蘭姆卡韓，奧丹姆" />
    </Connections>
  </Node>
  <Node name="馬紹爾觀測站，安戈洛環形山" continent="1" x="-7548.05" y="-1541.13" z="-271.05">
    <Connections>
      <Connection name="諾達希爾，海加爾" />
      <Connection name="艾森娜之林，海加爾" />
      <Connection name="艾維娜聖壇，海加爾" />
      <Connection name="蘭姆卡韓，奧丹姆" />
    </Connections>
  </Node>
  <Node name="棘齒城，北貧瘠之地" continent="1" x="-894.59" y="-3773.01" z="11.48">
    <Connections>
      <Connection name="諾達希爾，海加爾" />
      <Connection name="艾森娜之林，海加爾" />
      <Connection name="艾維娜聖壇，海加爾" />
      <Connection name="蘭姆卡韓，奧丹姆" />
    </Connections>
  </Node>
  <Node name="血色守望，血謎島" continent="530" x="-1933.27" y="-11954.6" z="57.19">
    <Connections>
      <Connection name="諾達希爾，海加爾" />
      <Connection name="艾森娜之林，海加爾" />
      <Connection name="艾維娜聖壇，海加爾" />
      <Connection name="蘭姆卡韓，奧丹姆" />
    </Connections>
  </Node>
  <Node name="艾克索達" continent="530" x="-3867.56" y="-11641.1" z="-137.664">
    <Connections>
      <Connection name="諾達希爾，海加爾" />
      <Connection name="艾森娜之林，海加爾" />
      <Connection name="艾維娜聖壇，海加爾" />
      <Connection name="蘭姆卡韓，奧丹姆" />
    </Connections>
  </Node>
  <Node name="翡翠聖地，費伍德森林" continent="1" x="3972.84" y="-1324.51" z="244.803">
    <Connections />
  </Node>
  <Node name="林歌神殿，梣谷" continent="1" x="3000.25" y="-3202.41" z="189.77">
    <Connections />
  </Node>
  <Node name="泥鏈營地，塵泥沼澤" continent="1" x="-4566.23" y="-3226.05" z="34.7">
    <Connections>
      <Connection name="諾達希爾，海加爾" />
      <Connection name="艾森娜之林，海加爾" />
      <Connection name="艾維娜聖壇，海加爾" />
      <Connection name="蘭姆卡韓，奧丹姆" />
    </Connections>
  </Node>
  <Node name="黑澗營地，梣谷" continent="1" x="3880.51" y="654.16" z="10.46">
    <Connections />
  </Node>
  <Node name="古樹之林，黑海岸" continent="1" x="4970.5" y="147.65" z="51.64">
    <Connections>
      <Connection name="諾達希爾，海加爾" />
      <Connection name="艾森娜之林，海加爾" />
      <Connection name="艾維娜聖壇，海加爾" />
      <Connection name="蘭姆卡韓，奧丹姆" />
    </Connections>
  </Node>
  <Node name="星塵尖塔，梣谷" continent="1" x="1905.11" y="-321.99" z="118.25">
    <Connections />
  </Node>
  <Node name="狂風堡，石爪山脈" continent="1" x="1268.51" y="432.87" z="95.56">
    <Connections />
  </Node>
  <Node name="北方遠征隊營地，石爪山脈" continent="1" x="237.88" y="-281.35" z="92.76">
    <Connections />
  </Node>
  <Node name="遠眺者之谷，石爪山脈" continent="1" x="973.94" y="2013.13" z="126.59">
    <Connections />
  </Node>
  <Node name="薩爾加德營地，淒涼之地" continent="1" x="-1694.53" y="2577.57" z="136.59">
    <Connections />
  </Node>
  <Node name="卡努姆林地，淒涼之地" continent="1" x="-1038.43" y="1637.99" z="60.56">
    <Connections />
  </Node>
  <Node name="桑克的居所，淒涼之地" continent="1" x="-534.04" y="1056.68" z="89.91">
    <Connections />
  </Node>
  <Node name="艾瑟雷索，淒涼之地" continent="1" x="-356.47" y="2478.9" z="75.95">
    <Connections />
  </Node>
  <Node name="苔蘚堆，安戈洛環形山" continent="1" x="-6958.44" y="-1095.24" z="-272.65">
    <Connections>
      <Connection name="諾達希爾，海加爾" />
      <Connection name="艾森娜之林，海加爾" />
      <Connection name="艾維娜聖壇，海加爾" />
      <Connection name="蘭姆卡韓，奧丹姆" />
    </Connections>
  </Node>
  <Node name="榮譽看臺，南貧瘠之地" continent="1" x="-335.2" y="-1532.44" z="87.51">
    <Connections />
  </Node>
  <Node name="北方城堡，南貧瘠之地" continent="1" x="-2124.21" y="-3561.79" z="100.89">
    <Connections>
      <Connection name="諾達希爾，海加爾" />
      <Connection name="艾森娜之林，海加爾" />
      <Connection name="艾維娜聖壇，海加爾" />
      <Connection name="蘭姆卡韓，奧丹姆" />
    </Connections>
  </Node>
  <Node name="凱旋堡壘，南貧瘠之地" continent="1" x="-3150.25" y="-2286.27" z="93.01">
    <Connections />
  </Node>
  <Node name="多蘭納爾，泰達希爾" continent="1" x="9873.1" y="977.698" z="1309.98">
    <Connections>
      <Connection name="諾達希爾，海加爾" />
      <Connection name="艾森娜之林，海加爾" />
      <Connection name="艾維娜聖壇，海加爾" />
      <Connection name="蘭姆卡韓，奧丹姆" />
    </Connections>
  </Node>
  <Node name="達納蘇斯，泰達希爾" continent="1" x="9968.8" y="2622.09" z="1316.08">
    <Connections>
      <Connection name="諾達希爾，海加爾" />
      <Connection name="艾森娜之林，海加爾" />
      <Connection name="艾維娜聖壇，海加爾" />
      <Connection name="蘭姆卡韓，奧丹姆" />
    </Connections>
  </Node>
  <Node name="菲茲爾與普茲克的高速駁船，千針石林" continent="1" x="-6075.37" y="-3913.44" z="21.6224">
    <Connections>
      <Connection name="諾達希爾，海加爾" />
      <Connection name="艾森娜之林，海加爾" />
      <Connection name="艾維娜聖壇，海加爾" />
      <Connection name="蘭姆卡韓，奧丹姆" />
    </Connections>
  </Node>
  <Node name="古斯坦挖掘場，塔納利斯" continent="1" x="-9493.71" y="-2953.99" z="12.6826">
    <Connections />
  </Node>
  <Node name="私酒商哨站，塔納利斯" continent="1" x="-8683.09" y="-4088.1" z="40.0553">
    <Connections />
  </Node>
  <Node name="暗色崗哨，石爪山脈" continent="1" x="1379.42" y="1034.86" z="165.088">
    <Connections />
  </Node>
  <Node name="艾維娜聖壇，海加爾" continent="1" master="43481" x="4987.87" y="-2676.19" z="1426.36">
    <Connections>
      <Connection name="洛丹諾，黑海岸" />
      <Connection name="魯瑟蘭村，泰達希爾" />
      <Connection name="塞拉摩，塵泥沼澤" />
      <Connection name="加基森，塔納利斯" />
      <Connection name="月光林地" />
      <Connection name="塞納里奧城堡，希利蘇斯" />
      <Connection name="馬紹爾觀測站，安戈洛環形山" />
      <Connection name="棘齒城，北貧瘠之地" />
      <Connection name="血色守望，血謎島" />
      <Connection name="艾克索達" />
      <Connection name="泥鏈營地，塵泥沼澤" />
      <Connection name="古樹之林，黑海岸" />
      <Connection name="苔蘚堆，安戈洛環形山" />
      <Connection name="北方城堡，南貧瘠之地" />
      <Connection name="多蘭納爾，泰達希爾" />
      <Connection name="達納蘇斯，泰達希爾" />
      <Connection name="菲茲爾與普茲克的高速駁船，千針石林" />
      <Connection name="艾森娜之林，海加爾" />
      <Connection name="諾達希爾，海加爾" />
      <Connection name="藍色守望，藍謎島" />
      <Connection name="蘭姆卡韓，奧丹姆" />
    </Connections>
  </Node>
  <Node name="艾森娜之林，海加爾" continent="1" master="41860" x="5163.51" y="-1760.58" z="1338.47">
    <Connections>
      <Connection name="洛丹諾，黑海岸" />
      <Connection name="魯瑟蘭村，泰達希爾" />
      <Connection name="塞拉摩，塵泥沼澤" />
      <Connection name="加基森，塔納利斯" />
      <Connection name="月光林地" />
      <Connection name="塞納里奧城堡，希利蘇斯" />
      <Connection name="馬紹爾觀測站，安戈洛環形山" />
      <Connection name="棘齒城，北貧瘠之地" />
      <Connection name="血色守望，血謎島" />
      <Connection name="艾克索達" />
      <Connection name="泥鏈營地，塵泥沼澤" />
      <Connection name="古樹之林，黑海岸" />
      <Connection name="苔蘚堆，安戈洛環形山" />
      <Connection name="北方城堡，南貧瘠之地" />
      <Connection name="多蘭納爾，泰達希爾" />
      <Connection name="達納蘇斯，泰達希爾" />
      <Connection name="菲茲爾與普茲克的高速駁船，千針石林" />
      <Connection name="諾達希爾，海加爾" />
      <Connection name="藍色守望，藍謎島" />
      <Connection name="艾維娜聖壇，海加爾" />
      <Connection name="蘭姆卡韓，奧丹姆" />
    </Connections>
  </Node>
  <Node name="夢旅者之眠，菲拉斯" continent="1" x="-3136.62" y="1951.67" z="41.5988">
    <Connections />
  </Node>
  <Node name="艾斯圖蘭之塔，菲拉斯" continent="1" x="-4863.64" y="1478.16" z="84.8475">
    <Connections />
  </Node>
  <Node name="語風林地，費伍德森林" continent="1" x="6078.51" y="-844.998" z="412.274">
    <Connections />
  </Node>
  <Node name="野性之心營地，費伍德森林" continent="1" x="4734.16" y="-883.806" z="342.934">
    <Connections />
  </Node>
  <Node name="索桑恩之門，海加爾" continent="1" x="4059.4" y="-3966.75" z="970.149">
    <Connections />
  </Node>
  <Node name="藍色守望，藍謎島" continent="530" x="-4130.08" y="-12520.5" z="44.3305">
    <Connections>
      <Connection name="諾達希爾，海加爾" />
      <Connection name="艾森娜之林，海加爾" />
      <Connection name="艾維娜聖壇，海加爾" />
      <Connection name="蘭姆卡韓，奧丹姆" />
    </Connections>
  </Node>
  <Node name="蘭姆卡韓，奧丹姆" continent="1" master="48275" x="-9415.02" y="-1042.97" z="113.396">
    <Connections>
      <Connection name="洛丹諾，黑海岸" />
      <Connection name="魯瑟蘭村，泰達希爾" />
      <Connection name="塞拉摩，塵泥沼澤" />
      <Connection name="加基森，塔納利斯" />
      <Connection name="月光林地" />
      <Connection name="塞納里奧城堡，希利蘇斯" />
      <Connection name="馬紹爾觀測站，安戈洛環形山" />
      <Connection name="棘齒城，北貧瘠之地" />
      <Connection name="血色守望，血謎島" />
      <Connection name="艾克索達" />
      <Connection name="泥鏈營地，塵泥沼澤" />
      <Connection name="古樹之林，黑海岸" />
      <Connection name="苔蘚堆，安戈洛環形山" />
      <Connection name="北方城堡，南貧瘠之地" />
      <Connection name="多蘭納爾，泰達希爾" />
      <Connection name="達納蘇斯，泰達希爾" />
      <Connection name="菲茲爾與普茲克的高速駁船，千針石林" />
      <Connection name="艾維娜聖壇，海加爾" />
      <Connection name="艾森娜之林，海加爾" />
      <Connection name="諾達希爾，海加爾" />
      <Connection name="藍色守望，藍謎島" />
    </Connections>
  </Node>
  <Node name="韋爾薩爾綠洲，奧丹姆" continent="1" x="-8375.47" y="791.259" z="148.422">
    <Connections />
  </Node>
  <Node name="舒諾茲營地，奧丹姆" continent="1" x="-10711.9" y="1059.62" z="24.149">
    <Connections />
  </Node>
  <Node name="瑪洛尼聖地，海加爾" continent="1" x="4397.79" y="-2107.53" z="1204.34">
    <Connections />
  </Node>
  <Node name="黑鐵峰，灼熱峽谷" continent="0" master="47927" x="-7123.06" y="-1236.63" z="290.131">
    <Connections>
      <Connection name="暴風城，艾爾文森林" />
      <Connection name="鐵爐堡，丹莫洛" />
      <Connection name="夜色鎮，暮色森林" />
      <Connection name="藏寶海灣，荊棘谷" />
      <Connection name="守望堡，詛咒之地" />
      <Connection name="反抗軍營地，荊棘谷" />
      <Connection name="破碎之日會所" />
      <Connection name="閃金鎮，艾爾文森林" />
      <Connection name="東谷伐木場，艾爾文森林" />
      <Connection name="李文斯頓堡壘，荊棘谷" />
      <Connection name="探險者協會挖掘場，荊棘谷" />
      <Connection name="卡拉諾斯，丹莫洛" />
      <Connection name="古博拉採掘場，丹莫洛" />
      <Connection name="高岸堡，暮光高地" />
    </Connections>
  </Node>
  <Node name="暴風城，艾爾文森林" continent="0" master="352" x="-8841.06" y="489.656" z="109.607">
    <Connections>
      <Connection name="黑鐵峰，灼熱峽谷" />
      <Connection name="鐵爐堡，丹莫洛" />
      <Connection name="夜色鎮，暮色森林" />
      <Connection name="藏寶海灣，荊棘谷" />
      <Connection name="守望堡，詛咒之地" />
      <Connection name="反抗軍營地，荊棘谷" />
      <Connection name="破碎之日會所" />
      <Connection name="閃金鎮，艾爾文森林" />
      <Connection name="東谷伐木場，艾爾文森林" />
      <Connection name="李文斯頓堡壘，荊棘谷" />
      <Connection name="探險者協會挖掘場，荊棘谷" />
      <Connection name="卡拉諾斯，丹莫洛" />
      <Connection name="古博拉採掘場，丹莫洛" />
      <Connection name="高岸堡，暮光高地" />
    </Connections>
  </Node>
  <Node name="哨兵嶺，西部荒野" continent="0" x="-10551.9" y="1034.39" z="56.9543">
    <Connections />
  </Node>
  <Node name="湖畔鎮，赤脊山" continent="0" x="-9429.1" y="-2231.4" z="68.65">
    <Connections />
  </Node>
  <Node name="鐵爐堡，丹莫洛" continent="0" x="-4821.78" y="-1155.44" z="502.21">
    <Connections>
      <Connection name="黑鐵峰，灼熱峽谷" />
      <Connection name="暴風城，艾爾文森林" />
      <Connection name="高岸堡，暮光高地" />
    </Connections>
  </Node>
  <Node name="米奈希爾港，濕地" continent="0" x="-3787.81" y="-777.696" z="1.5582">
    <Connections />
  </Node>
  <Node name="塞爾薩瑪，洛克莫丹" continent="0" x="-5421.91" y="-2930.01" z="347.25">
    <Connections />
  </Node>
  <Node name="夜色鎮，暮色森林" continent="0" x="-10515.5" y="-1261.65" z="41.34">
    <Connections>
      <Connection name="黑鐵峰，灼熱峽谷" />
      <Connection name="暴風城，艾爾文森林" />
      <Connection name="高岸堡，暮光高地" />
    </Connections>
  </Node>
  <Node name="避難谷地，阿拉希高地" continent="0" x="-1240.53" y="-2515.11" z="22.16">
    <Connections />
  </Node>
  <Node name="藏寶海灣，荊棘谷" continent="0" x="-14473" y="464.15" z="36.43">
    <Connections>
      <Connection name="黑鐵峰，灼熱峽谷" />
      <Connection name="暴風城，艾爾文森林" />
      <Connection name="高岸堡，暮光高地" />
    </Connections>
  </Node>
  <Node name="鷹巢山，辛特蘭" continent="0" x="283.74" y="-2002.76" z="194.74">
    <Connections />
  </Node>
  <Node name="守望堡，詛咒之地" continent="0" x="-11112.3" y="-3435.74" z="79.09">
    <Connections>
      <Connection name="黑鐵峰，灼熱峽谷" />
      <Connection name="暴風城，艾爾文森林" />
      <Connection name="高岸堡，暮光高地" />
    </Connections>
  </Node>
  <Node name="冰風營地，西瘟疫之地" continent="0" x="931.32" y="-1430.11" z="64.67">
    <Connections />
  </Node>
  <Node name="聖光之願禮拜堂，東瘟疫之地" continent="0" x="2271.09" y="-5340.8" z="87.11">
    <Connections />
  </Node>
  <Node name="摩根的崗哨，燃燒平原" continent="0" x="-8364.61" y="-2738.35" z="185.46">
    <Connections />
  </Node>
  <Node name="瑟銀哨塔，灼熱峽谷" continent="0" x="-6552.59" y="-1168.27" z="309.31">
    <Connections />
  </Node>
  <Node name="病木林哨塔，東瘟疫之地" continent="0" x="2965.55" y="-3033.61" z="126.929">
    <Connections />
  </Node>
  <Node name="北地哨塔，東瘟疫之地" continent="0" x="3134.26" y="-4354.78" z="133.463">
    <Connections />
  </Node>
  <Node name="東牆之塔，東瘟疫之地" continent="0" x="2524.44" y="-4769.56" z="104.087">
    <Connections />
  </Node>
  <Node name="皇冠哨塔，東瘟疫之地" continent="0" x="1876.4" y="-3693.32" z="157.687">
    <Connections />
  </Node>
  <Node name="反抗軍營地，荊棘谷" continent="0" x="-11344" y="-216.83" z="75.22">
    <Connections>
      <Connection name="黑鐵峰，灼熱峽谷" />
      <Connection name="暴風城，艾爾文森林" />
      <Connection name="高岸堡，暮光高地" />
    </Connections>
  </Node>
  <Node name="祖阿曼，鬼魂之地" continent="530" x="6789.79" y="-7747.58" z="126.51">
    <Connections />
  </Node>
  <Node name="破碎之日會所" continent="530" x="13012.7" y="-6908.37" z="9.58">
    <Connections>
      <Connection name="黑鐵峰，灼熱峽谷" />
      <Connection name="暴風城，艾爾文森林" />
      <Connection name="高岸堡，暮光高地" />
    </Connections>
  </Node>
  <Node name="索多里爾河，東瘟疫之地" continent="0" x="1935.97" y="-2694.48" z="61.9471">
    <Connections />
  </Node>
  <Node name="走私者之痕，瓦許伊爾" continent="0" x="-4588.05" y="3481.12" z="-102.718">
    <Connections />
  </Node>
  <Node name="銀浪谷地，瓦許伊爾" continent="0" x="-6105.61" y="4285.08" z="-350.5">
    <Connections />
  </Node>
  <Node name="寧靜港灣，瓦許伊爾" continent="0" x="-6616.4" y="4308.28" z="-564.077">
    <Connections />
  </Node>
  <Node name="黑裂灣，瓦許伊爾" continent="0" x="-6902.25" y="5943.82" z="-766.516">
    <Connections />
  </Node>
  <Node name="維爾加的避難所，濕地" continent="0" x="-3222.93" y="-1989.49" z="50.5475">
    <Connections />
  </Node>
  <Node name="綠意守望者之林，濕地" continent="0" x="-3306.65" y="-2718.69" z="20.4836">
    <Connections />
  </Node>
  <Node name="丹莫德，濕地" continent="0" x="-2656.54" y="-2464.28" z="80.3378">
    <Connections />
  </Node>
  <Node name="斯拉奇索勘察地，濕地" continent="0" x="-4113.6" y="-2741.21" z="18.9911">
    <Connections />
  </Node>
  <Node name="遠行者小屋，洛克莫丹" continent="0" x="-5668.31" y="-4253.44" z="407.015">
    <Connections />
  </Node>
  <Node name="閃金鎮，艾爾文森林" continent="0" x="-9433.99" y="85.1493" z="56.734">
    <Connections>
      <Connection name="黑鐵峰，灼熱峽谷" />
      <Connection name="暴風城，艾爾文森林" />
      <Connection name="高岸堡，暮光高地" />
    </Connections>
  </Node>
  <Node name="月溪鎮，西部荒野" continent="0" x="-10876.9" y="1542.88" z="54.5289">
    <Connections />
  </Node>
  <Node name="法布隆南瓜農場，西部荒野" continent="0" x="-9838.51" y="1273.93" z="40.7067">
    <Connections />
  </Node>
  <Node name="東谷伐木場，艾爾文森林" continent="0" x="-9475.71" y="-1306.74" z="44.1496">
    <Connections>
      <Connection name="黑鐵峰，灼熱峽谷" />
      <Connection name="暴風城，艾爾文森林" />
      <Connection name="高岸堡，暮光高地" />
    </Connections>
  </Node>
  <Node name="李文斯頓堡壘，荊棘谷" continent="0" x="-12828.8" y="-413.71" z="12.9666">
    <Connections>
      <Connection name="黑鐵峰，灼熱峽谷" />
      <Connection name="暴風城，艾爾文森林" />
      <Connection name="高岸堡，暮光高地" />
    </Connections>
  </Node>
  <Node name="探險者協會挖掘場，荊棘谷" continent="0" x="-13600.9" y="-85.5486" z="37.8078">
    <Connections>
      <Connection name="黑鐵峰，灼熱峽谷" />
      <Connection name="暴風城，艾爾文森林" />
      <Connection name="高岸堡，暮光高地" />
    </Connections>
  </Node>
  <Node name="岩風峽谷，赤脊山" continent="0" x="-9641.67" y="-3479.37" z="121.956">
    <Connections />
  </Node>
  <Node name="沼潮哨站，悲傷沼澤" continent="0" x="-10176.6" y="-3836.54" z="17.986">
    <Connections />
  </Node>
  <Node name="沼槳，悲傷沼澤" continent="0" x="-9737.08" y="-3890.72" z="22.73">
    <Connections />
  </Node>
  <Node name="避難營，悲傷沼澤" continent="0" x="-10118.6" y="-2852.48" z="23.4641">
    <Connections />
  </Node>
  <Node name="佛德林堡號，瓦許伊爾" continent="0" x="-7209.71" y="3925.85" z="14.7466">
    <Connections />
  </Node>
  <Node name="沙灘，瓦許伊爾" continent="0" x="-5310.85" y="3914.42" z="3.22433">
    <Connections />
  </Node>
  <Node name="止水營地，赤脊山" continent="0" x="-9446.64" y="-2836.99" z="64.5761">
    <Connections />
  </Node>
  <Node name="風暴之羽崗哨，辛特蘭" continent="0" x="312.326" y="-4105.36" z="118.289">
    <Connections />
  </Node>
  <Node name="卡拉諾斯，丹莫洛" continent="0" x="-5660.8" y="-494.851" z="397.008">
    <Connections>
      <Connection name="黑鐵峰，灼熱峽谷" />
      <Connection name="暴風城，艾爾文森林" />
      <Connection name="高岸堡，暮光高地" />
    </Connections>
  </Node>
  <Node name="古博拉採掘場，丹莫洛" continent="0" x="-5714.14" y="-1578.64" z="383.204">
    <Connections>
      <Connection name="黑鐵峰，灼熱峽谷" />
      <Connection name="暴風城，艾爾文森林" />
      <Connection name="高岸堡，暮光高地" />
    </Connections>
  </Node>
  <Node name="烏鴉嶺，暮色森林" continent="0" x="-10737.6" y="267.043" z="42.3478">
    <Connections />
  </Node>
  <Node name="光盾哨塔，東瘟疫之地" continent="0" x="2262.1" y="-4411.52" z="111.652">
    <Connections />
  </Node>
  <Node name="塵風挖掘場，荒蕪之地" continent="0" x="-6594.09" y="-3401.18" z="279.209">
    <Connections />
  </Node>
  <Node name="龍之口，荒蕪之地" continent="0" x="-7034.53" y="-2570.79" z="252.153">
    <Connections />
  </Node>
  <Node name="熔絲火光山間營地，荒蕪之地" continent="0" x="-6574.94" y="-3875.13" z="390.94">
    <Connections />
  </Node>
  <Node name="治癒者崗哨，西瘟疫之地" continent="0" x="1864.32" y="-1755.82" z="59.662">
    <Connections />
  </Node>
  <Node name="高岸堡，暮光高地" continent="0" master="47119" x="-4863.1" y="-6740.61" z="9.41677">
    <Connections>
      <Connection name="暴風城，艾爾文森林" />
      <Connection name="鐵爐堡，丹莫洛" />
      <Connection name="夜色鎮，暮色森林" />
      <Connection name="藏寶海灣，荊棘谷" />
      <Connection name="守望堡，詛咒之地" />
      <Connection name="反抗軍營地，荊棘谷" />
      <Connection name="破碎之日會所" />
      <Connection name="閃金鎮，艾爾文森林" />
      <Connection name="東谷伐木場，艾爾文森林" />
      <Connection name="李文斯頓堡壘，荊棘谷" />
      <Connection name="探險者協會挖掘場，荊棘谷" />
      <Connection name="卡拉諾斯，丹莫洛" />
      <Connection name="古博拉採掘場，丹莫洛" />
      <Connection name="黑鐵峰，灼熱峽谷" />
    </Connections>
  </Node>
  <Node name="勝利者崗哨，暮光高地" continent="0" x="-4170.55" y="-4748.93" z="126.787">
    <Connections />
  </Node>
  <Node name="火鬍巡防地，暮光高地" continent="0" x="-4183.9" y="-5620.15" z="25.2103">
    <Connections />
  </Node>
  <Node name="桑德瑪，暮光高地" continent="0" x="-3146.92" y="-4994.28" z="128.485">
    <Connections />
  </Node>
  <Node name="柯特海文，暮光高地" continent="0" x="-2689.43" y="-5427.53" z="190.207">
    <Connections />
  </Node>
  <Node name="壁爐谷，西瘟疫之地" continent="0" x="2839.78" y="-1500.51" z="146.089">
    <Connections />
  </Node>
  <Node name="燎星崗哨，燃燒平原" continent="0" x="-8092.26" y="-1025.79" z="132.666">
    <Connections />
  </Node>
  <Node name="鑿柄，燃燒平原" continent="0" x="-7865.93" y="-1919.53" z="144.722">
    <Connections />
  </Node>
  <Node name="坡東村，翠玉林" continent="870" master="66023" x="-307.2" y="-1762.77" z="61.5927">
    <Connections>
      <Connection name="珠鰭村，翠玉林" />
      <Connection name="潘家莊，四風峽" />
      <Connection name="草生群，四風峽" />
      <Connection name="半丘市集，四風峽" />
      <Connection name="石犁村，四風峽" />
      <Connection name="祝家守望站，喀撒朗蠻荒" />
    </Connections>
  </Node>
  <Node name="晨綻，翠玉林" continent="870" x="1503.71" y="-1832.13" z="246.2">
    <Connections>
      <Connection name="半丘市集，四風峽" />
      <Connection name="石犁村，四風峽" />
      <Connection name="祝家守望站，喀撒朗蠻荒" />
    </Connections>
  </Node>
  <Node name="落英園，翠玉林" continent="870" x="1600.66" y="-2530.27" z="152.212">
    <Connections />
  </Node>
  <Node name="玉廟庭，翠玉林" continent="870" x="773.247" y="-2358.96" z="120.98">
    <Connections />
  </Node>
  <Node name="斯里拉村，翠玉林" continent="870" x="2550.76" y="-2418.32" z="23.9507">
    <Connections />
  </Node>
  <Node name="帝王之兆，翠玉林" continent="870" x="2400.75" y="-2099.43" z="228.034">
    <Connections />
  </Node>
  <Node name="天僧寺，翠玉林" continent="870" x="2505.9" y="-1590.89" z="400.868">
    <Connections />
  </Node>
  <Node name="珠鰭村，翠玉林" continent="870" master="56737" x="-186.097" y="-2594.61" z="0.944614">
    <Connections>
      <Connection name="坡東村，翠玉林" />
      <Connection name="潘家莊，四風峽" />
      <Connection name="草生群，四風峽" />
      <Connection name="半丘市集，四風峽" />
      <Connection name="石犁村，四風峽" />
      <Connection name="祝家守望站，喀撒朗蠻荒" />
    </Connections>
  </Node>
  <Node name="潘家莊，四風峽" continent="870" master="60230" x="543.915" y="-637.814" z="257.775">
    <Connections>
      <Connection name="坡東村，翠玉林" />
      <Connection name="珠鰭村，翠玉林" />
      <Connection name="草生群，四風峽" />
      <Connection name="半丘市集，四風峽" />
      <Connection name="石犁村，四風峽" />
      <Connection name="祝家守望站，喀撒朗蠻荒" />
    </Connections>
  </Node>
  <Node name="半丘市集，四風峽" continent="870" master="60231" x="-221.326" y="464.559" z="185.442">
    <Connections>
      <Connection name="晨綻，翠玉林" />
      <Connection name="坡東村，翠玉林" />
      <Connection name="珠鰭村，翠玉林" />
      <Connection name="潘家莊，四風峽" />
      <Connection name="草生群，四風峽" />
      <Connection name="石犁村，四風峽" />
      <Connection name="祝家守望站，喀撒朗蠻荒" />
    </Connections>
  </Node>
  <Node name="祝家守望站，喀撒朗蠻荒" continent="870" master="60232" x="-375.684" y="-647.965" z="117.516">
    <Connections>
      <Connection name="晨綻，翠玉林" />
      <Connection name="坡東村，翠玉林" />
      <Connection name="珠鰭村，翠玉林" />
      <Connection name="潘家莊，四風峽" />
      <Connection name="半丘市集，四風峽" />
      <Connection name="石犁村，四風峽" />
      <Connection name="草生群，四風峽" />
    </Connections>
  </Node>
  <Node name="侵略哨站，喀撒朗蠻荒" continent="870" x="-1125.31" y="-227.747" z="31.3673">
    <Connections />
  </Node>
  <Node name="石犁村，四風峽" continent="870" master="58843" x="-436.54" y="1886.7" z="131.13">
    <Connections>
      <Connection name="晨綻，翠玉林" />
      <Connection name="坡東村，翠玉林" />
      <Connection name="珠鰭村，翠玉林" />
      <Connection name="潘家莊，四風峽" />
      <Connection name="半丘市集，四風峽" />
      <Connection name="草生群，四風峽" />
      <Connection name="祝家守望站，喀撒朗蠻荒" />
    </Connections>
  </Node>
  <Node name="哨兵營地，喀撒朗蠻荒" continent="870" x="-1156.61" y="1770.38" z="16.989">
    <Connections />
  </Node>
  <Node name="赤吉搖籃，喀撒朗蠻荒" continent="870" x="-2082.3" y="1483.63" z="0.550604">
    <Connections />
  </Node>
  <Node name="瑪里斯塔，喀撒朗蠻荒" continent="870" x="-2504.09" y="491.583" z="2.33204">
    <Connections />
  </Node>
  <Node name="濱南村，崑萊峰" continent="870" x="1690.11" y="303.958" z="478.587">
    <Connections />
  </Node>
  <Node name="白虎寺，崑萊峰" continent="870" x="3504.04" y="690.677" z="608.185">
    <Connections />
  </Node>
  <Node name="西風之眠，崑萊峰" continent="870" x="2103.35" y="1463.83" z="487.886">
    <Connections />
  </Node>
  <Node name="驟晴村，崑萊峰" continent="870" x="4362.96" y="932.118" z="110.039">
    <Connections />
  </Node>
  <Node name="獨罈集，崑萊峰" continent="870" x="3124.52" y="1224.28" z="654.231">
    <Connections />
  </Node>
  <Node name="柯沓營地，崑萊峰" continent="870" x="2716.43" y="2163.31" z="589.098">
    <Connections />
  </Node>
  <Node name="影潘後援地，崑萊峰" continent="870" x="1880.59" y="2088.58" z="500.854">
    <Connections />
  </Node>
  <Node name="冬綻，崑萊峰" continent="870" x="3151.85" y="2677.76" z="579.735">
    <Connections />
  </Node>
  <Node name="霧隱客棧，朦朧天梯" continent="870" x="784.899" y="-203.67" z="402.192">
    <Connections />
  </Node>
  <Node name="草生群，四風峽" continent="870" master="62658" x="460.54" y="-100.467" z="179.535">
    <Connections>
      <Connection name="坡東村，翠玉林" />
      <Connection name="珠鰭村，翠玉林" />
      <Connection name="潘家莊，四風峽" />
      <Connection name="半丘市集，四風峽" />
      <Connection name="石犁村，四風峽" />
      <Connection name="祝家守望站，喀撒朗蠻荒" />
    </Connections>
  </Node>
  <Node name="長陰哨站，螳螂荒原" continent="870" x="2363.23" y="2994.39" z="420.568">
    <Connections />
  </Node>
  <Node name="高仁前線，螳螂荒原" continent="870" x="1440.72" y="2804.49" z="301.922">
    <Connections />
  </Node>
  <Node name="任賽看守站，螳螂荒原" continent="870" x="1531.73" y="3963.7" z="227.666">
    <Connections />
  </Node>
  <Node name="影潘要塞，螳螂荒原" continent="870" x="1803.32" y="4204.23" z="157.508">
    <Connections />
  </Node>
  <Node name="七星廟，恆春谷" continent="870" x="896.453" y="334.351" z="506.085">
    <Connections />
  </Node>
  <Node name="卡拉西斐斯，悚然荒野" continent="870" x="172.663" y="3152.25" z="215.54">
    <Connections />
  </Node>
  <Node name="濕佬的賭注，悚然荒野" continent="870" x="-1086.21" y="3136.19" z="0.9831">
    <Connections />
  </Node>
  <Node name="日落釀酒園，悚然荒野" continent="870" x="982.677" y="3451.86" z="256.77">
    <Connections />
  </Node>
  <Node name="蟠龍脊，恆春谷" continent="870" x="611.365" y="2125.03" z="368.355">
    <Connections />
  </Node>
  <Node name="蟠龍之望，翠玉林" continent="870" x="465.856" y="-1558.56" z="154.886">
    <Connections />
  </Node>
  <Node name="潮間帶，悚然荒野" continent="870" x="-570.405" y="3859.79" z="0.734358">
    <Connections />
  </Node>
  <Node name="雄獅壁壘，悚然荒野" continent="870" x="234.406" y="2198.03" z="271.477">
    <Connections />
  </Node>
  <Node name="嗶啵的墜毀點，巨獸島" continent="870" x="5753.76" y="1255.55" z="1.51476">
    <Connections />
  </Node>
  <Node name="永恆之島，土水平臺" continent="870" x="-901.37" y="-4639.12" z="4.96101">
    <Connections />
  </Node>
  <Node name="落月之地 (聯盟)，影月谷" continent="1116" master="81103" x="1866.56" y="219.467" z="77.5279">
    <Connections>
      <Connection name="安伯瑞村，影月谷" />
      <Connection name="埃羅多爾 (聯盟)，影月谷" />
      <Connection name="暴風之盾 (聯盟)，艾斯蘭" />
      <Connection name="荒林小徑，格古隆德" />
      <Connection name="暮光林地，影月谷" />
      <Connection name="達克瑞姆，影月谷" />
      <Connection name="高地之路，格古隆德" />
      <Connection name="烏瑞恩堡 (聯盟)，塔拉多爾" />
      <Connection name="贊格拉，塔拉多爾" />
      <Connection name="救贖高崗，塔拉多爾" />
      <Connection name="泰洛卡避難所，塔拉多爾" />
      <Connection name="烏鴉鉤，阿拉卡山" />
      <Connection name="維爾泰洛克，阿拉卡山" />
      <Connection name="南埠，阿拉卡山" />
      <Connection name="急嘯零件廠，阿拉卡山" />
      <Connection name="頂尖挖掘場，阿拉卡山" />
      <Connection name="泰拉蕊哨站，納葛蘭" />
      <Connection name="試煉競技場，納葛蘭" />
    </Connections>
  </Node>
  <Node name="安伯瑞村，影月谷" continent="1116" master="76840" x="918.264" y="-792.361" z="-28.8338">
    <Connections>
      <Connection name="落月之地 (聯盟)，影月谷" />
      <Connection name="埃羅多爾 (聯盟)，影月谷" />
      <Connection name="暴風之盾 (聯盟)，艾斯蘭" />
      <Connection name="暮光林地，影月谷" />
      <Connection name="達克瑞姆，影月谷" />
      <Connection name="荒林小徑，格古隆德" />
      <Connection name="高地之路，格古隆德" />
      <Connection name="烏瑞恩堡 (聯盟)，塔拉多爾" />
      <Connection name="贊格拉，塔拉多爾" />
      <Connection name="救贖高崗，塔拉多爾" />
      <Connection name="泰洛卡避難所，塔拉多爾" />
      <Connection name="烏鴉鉤，阿拉卡山" />
      <Connection name="維爾泰洛克，阿拉卡山" />
      <Connection name="南埠，阿拉卡山" />
      <Connection name="急嘯零件廠，阿拉卡山" />
      <Connection name="頂尖挖掘場，阿拉卡山" />
      <Connection name="泰拉蕊哨站，納葛蘭" />
      <Connection name="試煉競技場，納葛蘭" />
    </Connections>
  </Node>
  <Node name="暮光林地，影月谷" continent="1116" master="76839" x="195.236" y="-459.2" z="-3.95986">
    <Connections>
      <Connection name="安伯瑞村，影月谷" />
      <Connection name="暴風之盾 (聯盟)，艾斯蘭" />
      <Connection name="埃羅多爾 (聯盟)，影月谷" />
      <Connection name="落月之地 (聯盟)，影月谷" />
      <Connection name="荒林小徑，格古隆德" />
      <Connection name="達克瑞姆，影月谷" />
      <Connection name="高地之路，格古隆德" />
      <Connection name="烏瑞恩堡 (聯盟)，塔拉多爾" />
      <Connection name="贊格拉，塔拉多爾" />
      <Connection name="救贖高崗，塔拉多爾" />
      <Connection name="泰洛卡避難所，塔拉多爾" />
      <Connection name="烏鴉鉤，阿拉卡山" />
      <Connection name="維爾泰洛克，阿拉卡山" />
      <Connection name="南埠，阿拉卡山" />
      <Connection name="急嘯零件廠，阿拉卡山" />
      <Connection name="頂尖挖掘場，阿拉卡山" />
      <Connection name="泰拉蕊哨站，納葛蘭" />
      <Connection name="試煉競技場，納葛蘭" />
    </Connections>
  </Node>
  <Node name="光明之路，影月谷" continent="1116" x="602.698" y="-1710.45" z="26.4837">
    <Connections />
  </Node>
  <Node name="流放者高地，影月谷" continent="1116" x="1526.38" y="-788.891" z="43.0647">
    <Connections />
  </Node>
  <Node name="血槌熔渣礦場，霜火峰" continent="1116" x="7399.45" y="4358.41" z="126.406">
    <Connections />
  </Node>
  <Node name="暴風之盾 (聯盟)，艾斯蘭" continent="1116" master="85959" x="3685.15" y="-3840.47" z="44.9819">
    <Connections>
      <Connection name="安伯瑞村，影月谷" />
      <Connection name="埃羅多爾 (聯盟)，影月谷" />
      <Connection name="落月之地 (聯盟)，影月谷" />
      <Connection name="荒林小徑，格古隆德" />
      <Connection name="暮光林地，影月谷" />
      <Connection name="達克瑞姆，影月谷" />
      <Connection name="高地之路，格古隆德" />
      <Connection name="烏瑞恩堡 (聯盟)，塔拉多爾" />
      <Connection name="贊格拉，塔拉多爾" />
      <Connection name="救贖高崗，塔拉多爾" />
      <Connection name="泰洛卡避難所，塔拉多爾" />
      <Connection name="烏鴉鉤，阿拉卡山" />
      <Connection name="維爾泰洛克，阿拉卡山" />
      <Connection name="南埠，阿拉卡山" />
      <Connection name="急嘯零件廠，阿拉卡山" />
      <Connection name="頂尖挖掘場，阿拉卡山" />
      <Connection name="泰拉蕊哨站，納葛蘭" />
      <Connection name="試煉競技場，納葛蘭" />
    </Connections>
  </Node>
  <Node name="贊格拉，塔拉多爾" continent="1116" master="80932" x="3418.78" y="1040.15" z="178.085">
    <Connections>
      <Connection name="安伯瑞村，影月谷" />
      <Connection name="暮光林地，影月谷" />
      <Connection name="暴風之盾 (聯盟)，艾斯蘭" />
      <Connection name="烏瑞恩堡 (聯盟)，塔拉多爾" />
      <Connection name="撒塔斯城，塔拉多爾" />
      <Connection name="隱士的居所，塔拉多爾" />
      <Connection name="達克瑞姆，影月谷" />
      <Connection name="埃羅多爾 (聯盟)，影月谷" />
      <Connection name="落月之地 (聯盟)，影月谷" />
      <Connection name="荒林小徑，格古隆德" />
      <Connection name="高地之路，格古隆德" />
      <Connection name="救贖高崗，塔拉多爾" />
      <Connection name="泰洛卡避難所，塔拉多爾" />
      <Connection name="烏鴉鉤，阿拉卡山" />
      <Connection name="維爾泰洛克，阿拉卡山" />
      <Connection name="南埠，阿拉卡山" />
      <Connection name="急嘯零件廠，阿拉卡山" />
      <Connection name="頂尖挖掘場，阿拉卡山" />
      <Connection name="泰拉蕊哨站，納葛蘭" />
      <Connection name="試煉競技場，納葛蘭" />
    </Connections>
  </Node>
  <Node name="烏瑞恩堡 (聯盟)，塔拉多爾" continent="1116" master="81060" x="3576.81" y="1669.4" z="172.792">
    <Connections>
      <Connection name="安伯瑞村，影月谷" />
      <Connection name="暮光林地，影月谷" />
      <Connection name="暴風之盾 (聯盟)，艾斯蘭" />
      <Connection name="達克瑞姆，影月谷" />
      <Connection name="埃羅多爾 (聯盟)，影月谷" />
      <Connection name="落月之地 (聯盟)，影月谷" />
      <Connection name="荒林小徑，格古隆德" />
      <Connection name="高地之路，格古隆德" />
      <Connection name="贊格拉，塔拉多爾" />
      <Connection name="救贖高崗，塔拉多爾" />
      <Connection name="撒塔斯城，塔拉多爾" />
      <Connection name="隱士的居所，塔拉多爾" />
      <Connection name="泰洛卡避難所，塔拉多爾" />
      <Connection name="烏鴉鉤，阿拉卡山" />
      <Connection name="維爾泰洛克，阿拉卡山" />
      <Connection name="南埠，阿拉卡山" />
      <Connection name="急嘯零件廠，阿拉卡山" />
      <Connection name="頂尖挖掘場，阿拉卡山" />
      <Connection name="泰拉蕊哨站，納葛蘭" />
      <Connection name="試煉競技場，納葛蘭" />
    </Connections>
  </Node>
  <Node name="救贖高崗，塔拉多爾" continent="1116" master="81061" x="3407.73" y="2062" z="160.398">
    <Connections>
      <Connection name="安伯瑞村，影月谷" />
      <Connection name="暮光林地，影月谷" />
      <Connection name="暴風之盾 (聯盟)，艾斯蘭" />
      <Connection name="贊格拉，塔拉多爾" />
      <Connection name="烏瑞恩堡 (聯盟)，塔拉多爾" />
      <Connection name="撒塔斯城，塔拉多爾" />
      <Connection name="隱士的居所，塔拉多爾" />
      <Connection name="達克瑞姆，影月谷" />
      <Connection name="埃羅多爾 (聯盟)，影月谷" />
      <Connection name="落月之地 (聯盟)，影月谷" />
      <Connection name="荒林小徑，格古隆德" />
      <Connection name="高地之路，格古隆德" />
      <Connection name="泰洛卡避難所，塔拉多爾" />
      <Connection name="烏鴉鉤，阿拉卡山" />
      <Connection name="維爾泰洛克，阿拉卡山" />
      <Connection name="南埠，阿拉卡山" />
      <Connection name="急嘯零件廠，阿拉卡山" />
      <Connection name="頂尖挖掘場，阿拉卡山" />
      <Connection name="泰拉蕊哨站，納葛蘭" />
      <Connection name="試煉競技場，納葛蘭" />
    </Connections>
  </Node>
  <Node name="撒塔斯城，塔拉多爾" continent="1116" x="2727.16" y="2777" z="242.933">
    <Connections>
      <Connection name="贊格拉，塔拉多爾" />
      <Connection name="救贖高崗，塔拉多爾" />
      <Connection name="烏瑞恩堡 (聯盟)，塔拉多爾" />
      <Connection name="泰洛卡避難所，塔拉多爾" />
      <Connection name="烏鴉鉤，阿拉卡山" />
      <Connection name="維爾泰洛克，阿拉卡山" />
      <Connection name="南埠，阿拉卡山" />
      <Connection name="急嘯零件廠，阿拉卡山" />
      <Connection name="頂尖挖掘場，阿拉卡山" />
      <Connection name="泰拉蕊哨站，納葛蘭" />
      <Connection name="試煉競技場，納葛蘭" />
    </Connections>
  </Node>
  <Node name="隱士的居所，塔拉多爾" continent="1116" x="2171.82" y="1059.22" z="112.517">
    <Connections>
      <Connection name="贊格拉，塔拉多爾" />
      <Connection name="救贖高崗，塔拉多爾" />
      <Connection name="烏瑞恩堡 (聯盟)，塔拉多爾" />
      <Connection name="泰洛卡避難所，塔拉多爾" />
      <Connection name="烏鴉鉤，阿拉卡山" />
      <Connection name="維爾泰洛克，阿拉卡山" />
      <Connection name="南埠，阿拉卡山" />
      <Connection name="急嘯零件廠，阿拉卡山" />
      <Connection name="頂尖挖掘場，阿拉卡山" />
      <Connection name="泰拉蕊哨站，納葛蘭" />
      <Connection name="試煉競技場，納葛蘭" />
    </Connections>
  </Node>
  <Node name="懲戒崗哨，塔拉多爾" continent="1116" x="1378.4" y="3318.52" z="138.134">
    <Connections />
  </Node>
  <Node name="主教避難所，塔拉多爾" continent="1116" x="1696.5" y="2561.35" z="133.659">
    <Connections />
  </Node>
  <Node name="泰洛卡避難所，塔拉多爾" continent="1116" master="81354" x="2158.65" y="1634.47" z="131.817">
    <Connections>
      <Connection name="安伯瑞村，影月谷" />
      <Connection name="暮光林地，影月谷" />
      <Connection name="暴風之盾 (聯盟)，艾斯蘭" />
      <Connection name="贊格拉，塔拉多爾" />
      <Connection name="烏瑞恩堡 (聯盟)，塔拉多爾" />
      <Connection name="救贖高崗，塔拉多爾" />
      <Connection name="撒塔斯城，塔拉多爾" />
      <Connection name="隱士的居所，塔拉多爾" />
      <Connection name="達克瑞姆，影月谷" />
      <Connection name="埃羅多爾 (聯盟)，影月谷" />
      <Connection name="落月之地 (聯盟)，影月谷" />
      <Connection name="荒林小徑，格古隆德" />
      <Connection name="高地之路，格古隆德" />
      <Connection name="烏鴉鉤，阿拉卡山" />
      <Connection name="維爾泰洛克，阿拉卡山" />
      <Connection name="南埠，阿拉卡山" />
      <Connection name="急嘯零件廠，阿拉卡山" />
      <Connection name="頂尖挖掘場，阿拉卡山" />
      <Connection name="泰拉蕊哨站，納葛蘭" />
      <Connection name="試煉競技場，納葛蘭" />
    </Connections>
  </Node>
  <Node name="達克瑞姆，影月谷" continent="1116" master="81284" x="128.569" y="-1555.75" z="31.4826">
    <Connections>
      <Connection name="安伯瑞村，影月谷" />
      <Connection name="暮光林地，影月谷" />
      <Connection name="暴風之盾 (聯盟)，艾斯蘭" />
      <Connection name="埃羅多爾 (聯盟)，影月谷" />
      <Connection name="落月之地 (聯盟)，影月谷" />
      <Connection name="荒林小徑，格古隆德" />
      <Connection name="高地之路，格古隆德" />
      <Connection name="烏瑞恩堡 (聯盟)，塔拉多爾" />
      <Connection name="贊格拉，塔拉多爾" />
      <Connection name="救贖高崗，塔拉多爾" />
      <Connection name="泰洛卡避難所，塔拉多爾" />
      <Connection name="烏鴉鉤，阿拉卡山" />
      <Connection name="維爾泰洛克，阿拉卡山" />
      <Connection name="南埠，阿拉卡山" />
      <Connection name="急嘯零件廠，阿拉卡山" />
      <Connection name="頂尖挖掘場，阿拉卡山" />
      <Connection name="泰拉蕊哨站，納葛蘭" />
      <Connection name="試煉競技場，納葛蘭" />
    </Connections>
  </Node>
  <Node name="埃羅多爾 (聯盟)，影月谷" continent="1116" master="81289" x="1240.2" y="-1666.43" z="44.8835">
    <Connections>
      <Connection name="安伯瑞村，影月谷" />
      <Connection name="落月之地 (聯盟)，影月谷" />
      <Connection name="暴風之盾 (聯盟)，艾斯蘭" />
      <Connection name="暮光林地，影月谷" />
      <Connection name="達克瑞姆，影月谷" />
      <Connection name="荒林小徑，格古隆德" />
      <Connection name="高地之路，格古隆德" />
      <Connection name="烏瑞恩堡 (聯盟)，塔拉多爾" />
      <Connection name="贊格拉，塔拉多爾" />
      <Connection name="救贖高崗，塔拉多爾" />
      <Connection name="泰洛卡避難所，塔拉多爾" />
      <Connection name="烏鴉鉤，阿拉卡山" />
      <Connection name="維爾泰洛克，阿拉卡山" />
      <Connection name="南埠，阿拉卡山" />
      <Connection name="急嘯零件廠，阿拉卡山" />
      <Connection name="頂尖挖掘場，阿拉卡山" />
      <Connection name="泰拉蕊哨站，納葛蘭" />
      <Connection name="試煉競技場，納葛蘭" />
    </Connections>
  </Node>
  <Node name="索奎薩爾高地，影月谷" continent="1116" x="-799.674" y="-671.424" z="107.102">
    <Connections />
  </Node>
  <Node name="南埠，阿拉卡山" continent="1116" master="83567" x="-1117.45" y="2316.97" z="1.96073">
    <Connections>
      <Connection name="安伯瑞村，影月谷" />
      <Connection name="暮光林地，影月谷" />
      <Connection name="暴風之盾 (聯盟)，艾斯蘭" />
      <Connection name="贊格拉，塔拉多爾" />
      <Connection name="烏瑞恩堡 (聯盟)，塔拉多爾" />
      <Connection name="救贖高崗，塔拉多爾" />
      <Connection name="撒塔斯城，塔拉多爾" />
      <Connection name="隱士的居所，塔拉多爾" />
      <Connection name="泰洛卡避難所，塔拉多爾" />
      <Connection name="達克瑞姆，影月谷" />
      <Connection name="埃羅多爾 (聯盟)，影月谷" />
      <Connection name="落月之地 (聯盟)，影月谷" />
      <Connection name="維爾泰洛克，阿拉卡山" />
      <Connection name="烏鴉鉤，阿拉卡山" />
      <Connection name="荒林小徑，格古隆德" />
      <Connection name="高地之路，格古隆德" />
      <Connection name="急嘯零件廠，阿拉卡山" />
      <Connection name="頂尖挖掘場，阿拉卡山" />
      <Connection name="泰拉蕊哨站，納葛蘭" />
      <Connection name="試煉競技場，納葛蘭" />
    </Connections>
  </Node>
  <Node name="試煉競技場，納葛蘭" continent="1116" master="83924" x="3040.78" y="4783.08" z="128.275">
    <Connections>
      <Connection name="安伯瑞村，影月谷" />
      <Connection name="暮光林地，影月谷" />
      <Connection name="暴風之盾 (聯盟)，艾斯蘭" />
      <Connection name="贊格拉，塔拉多爾" />
      <Connection name="烏瑞恩堡 (聯盟)，塔拉多爾" />
      <Connection name="救贖高崗，塔拉多爾" />
      <Connection name="撒塔斯城，塔拉多爾" />
      <Connection name="隱士的居所，塔拉多爾" />
      <Connection name="泰洛卡避難所，塔拉多爾" />
      <Connection name="達克瑞姆，影月谷" />
      <Connection name="埃羅多爾 (聯盟)，影月谷" />
      <Connection name="落月之地 (聯盟)，影月谷" />
      <Connection name="南埠，阿拉卡山" />
      <Connection name="泰拉蕊哨站，納葛蘭" />
      <Connection name="維爾泰洛克，阿拉卡山" />
      <Connection name="急嘯零件廠，阿拉卡山" />
      <Connection name="頂尖挖掘場，阿拉卡山" />
      <Connection name="烏鴉鉤，阿拉卡山" />
      <Connection name="荒林小徑，格古隆德" />
      <Connection name="高地之路，格古隆德" />
    </Connections>
  </Node>
  <Node name="元素王座，納葛蘭" continent="1116" x="3918.79" y="5131.45" z="62.728">
    <Connections />
  </Node>
  <Node name="泰拉蕊哨站，納葛蘭" continent="1116" master="82309" x="2594.25" y="5700.63" z="100.536">
    <Connections>
      <Connection name="安伯瑞村，影月谷" />
      <Connection name="暮光林地，影月谷" />
      <Connection name="暴風之盾 (聯盟)，艾斯蘭" />
      <Connection name="贊格拉，塔拉多爾" />
      <Connection name="烏瑞恩堡 (聯盟)，塔拉多爾" />
      <Connection name="救贖高崗，塔拉多爾" />
      <Connection name="撒塔斯城，塔拉多爾" />
      <Connection name="隱士的居所，塔拉多爾" />
      <Connection name="泰洛卡避難所，塔拉多爾" />
      <Connection name="達克瑞姆，影月谷" />
      <Connection name="埃羅多爾 (聯盟)，影月谷" />
      <Connection name="落月之地 (聯盟)，影月谷" />
      <Connection name="南埠，阿拉卡山" />
      <Connection name="維爾泰洛克，阿拉卡山" />
      <Connection name="急嘯零件廠，阿拉卡山" />
      <Connection name="頂尖挖掘場，阿拉卡山" />
      <Connection name="烏鴉鉤，阿拉卡山" />
      <Connection name="荒林小徑，格古隆德" />
      <Connection name="高地之路，格古隆德" />
      <Connection name="試煉競技場，納葛蘭" />
    </Connections>
  </Node>
  <Node name="伊芮爾崗哨，納葛蘭" continent="1116" x="3384.17" y="5755.58" z="39.1851">
    <Connections />
  </Node>
  <Node name="維爾泰洛克，阿拉卡山" continent="1116" master="84498" x="-398.988" y="1880.12" z="51.2684">
    <Connections>
      <Connection name="安伯瑞村，影月谷" />
      <Connection name="暮光林地，影月谷" />
      <Connection name="暴風之盾 (聯盟)，艾斯蘭" />
      <Connection name="贊格拉，塔拉多爾" />
      <Connection name="烏瑞恩堡 (聯盟)，塔拉多爾" />
      <Connection name="救贖高崗，塔拉多爾" />
      <Connection name="撒塔斯城，塔拉多爾" />
      <Connection name="隱士的居所，塔拉多爾" />
      <Connection name="泰洛卡避難所，塔拉多爾" />
      <Connection name="達克瑞姆，影月谷" />
      <Connection name="埃羅多爾 (聯盟)，影月谷" />
      <Connection name="落月之地 (聯盟)，影月谷" />
      <Connection name="烏鴉鉤，阿拉卡山" />
      <Connection name="荒林小徑，格古隆德" />
      <Connection name="高地之路，格古隆德" />
      <Connection name="南埠，阿拉卡山" />
      <Connection name="急嘯零件廠，阿拉卡山" />
      <Connection name="頂尖挖掘場，阿拉卡山" />
      <Connection name="泰拉蕊哨站，納葛蘭" />
      <Connection name="試煉競技場，納葛蘭" />
    </Connections>
  </Node>
  <Node name="鴉爪崗哨，阿拉卡山" continent="1116" x="-335.451" y="926.622" z="75.2153">
    <Connections />
  </Node>
  <Node name="急嘯零件廠，阿拉卡山" continent="1116" master="82511" x="-1579.14" y="993.09" z="8.08963">
    <Connections>
      <Connection name="安伯瑞村，影月谷" />
      <Connection name="暮光林地，影月谷" />
      <Connection name="暴風之盾 (聯盟)，艾斯蘭" />
      <Connection name="贊格拉，塔拉多爾" />
      <Connection name="烏瑞恩堡 (聯盟)，塔拉多爾" />
      <Connection name="救贖高崗，塔拉多爾" />
      <Connection name="撒塔斯城，塔拉多爾" />
      <Connection name="隱士的居所，塔拉多爾" />
      <Connection name="泰洛卡避難所，塔拉多爾" />
      <Connection name="達克瑞姆，影月谷" />
      <Connection name="埃羅多爾 (聯盟)，影月谷" />
      <Connection name="落月之地 (聯盟)，影月谷" />
      <Connection name="南埠，阿拉卡山" />
      <Connection name="維爾泰洛克，阿拉卡山" />
      <Connection name="烏鴉鉤，阿拉卡山" />
      <Connection name="荒林小徑，格古隆德" />
      <Connection name="高地之路，格古隆德" />
      <Connection name="頂尖挖掘場，阿拉卡山" />
      <Connection name="泰拉蕊哨站，納葛蘭" />
      <Connection name="試煉競技場，納葛蘭" />
    </Connections>
  </Node>
  <Node name="堡壘高地，格古隆德" continent="1116" x="4552.27" y="1274.56" z="144.928">
    <Connections />
  </Node>
  <Node name="頂尖挖掘場，阿拉卡山" continent="1116" master="84509" x="387.542" y="2442.73" z="19.3169">
    <Connections>
      <Connection name="安伯瑞村，影月谷" />
      <Connection name="暮光林地，影月谷" />
      <Connection name="暴風之盾 (聯盟)，艾斯蘭" />
      <Connection name="贊格拉，塔拉多爾" />
      <Connection name="烏瑞恩堡 (聯盟)，塔拉多爾" />
      <Connection name="救贖高崗，塔拉多爾" />
      <Connection name="撒塔斯城，塔拉多爾" />
      <Connection name="隱士的居所，塔拉多爾" />
      <Connection name="泰洛卡避難所，塔拉多爾" />
      <Connection name="達克瑞姆，影月谷" />
      <Connection name="埃羅多爾 (聯盟)，影月谷" />
      <Connection name="落月之地 (聯盟)，影月谷" />
      <Connection name="南埠，阿拉卡山" />
      <Connection name="維爾泰洛克，阿拉卡山" />
      <Connection name="急嘯零件廠，阿拉卡山" />
      <Connection name="烏鴉鉤，阿拉卡山" />
      <Connection name="荒林小徑，格古隆德" />
      <Connection name="高地之路，格古隆德" />
      <Connection name="泰拉蕊哨站，納葛蘭" />
      <Connection name="試煉競技場，納葛蘭" />
    </Connections>
  </Node>
  <Node name="烏鴉鉤，阿拉卡山" continent="1116" master="84515" x="128.615" y="1544.63" z="-1.72825">
    <Connections>
      <Connection name="安伯瑞村，影月谷" />
      <Connection name="暮光林地，影月谷" />
      <Connection name="暴風之盾 (聯盟)，艾斯蘭" />
      <Connection name="贊格拉，塔拉多爾" />
      <Connection name="烏瑞恩堡 (聯盟)，塔拉多爾" />
      <Connection name="救贖高崗，塔拉多爾" />
      <Connection name="撒塔斯城，塔拉多爾" />
      <Connection name="隱士的居所，塔拉多爾" />
      <Connection name="泰洛卡避難所，塔拉多爾" />
      <Connection name="達克瑞姆，影月谷" />
      <Connection name="埃羅多爾 (聯盟)，影月谷" />
      <Connection name="落月之地 (聯盟)，影月谷" />
      <Connection name="荒林小徑，格古隆德" />
      <Connection name="高地之路，格古隆德" />
      <Connection name="維爾泰洛克，阿拉卡山" />
      <Connection name="南埠，阿拉卡山" />
      <Connection name="急嘯零件廠，阿拉卡山" />
      <Connection name="頂尖挖掘場，阿拉卡山" />
      <Connection name="泰拉蕊哨站，納葛蘭" />
      <Connection name="試煉競技場，納葛蘭" />
    </Connections>
  </Node>
  <Node name="荒林小徑，格古隆德" continent="1116" master="81884" x="6456.1" y="-174.755" z="120.071">
    <Connections>
      <Connection name="暴風之盾 (聯盟)，艾斯蘭" />
      <Connection name="落月之地 (聯盟)，影月谷" />
      <Connection name="暮光林地，影月谷" />
      <Connection name="達克瑞姆，影月谷" />
      <Connection name="安伯瑞村，影月谷" />
      <Connection name="埃羅多爾 (聯盟)，影月谷" />
      <Connection name="高地之路，格古隆德" />
      <Connection name="烏瑞恩堡 (聯盟)，塔拉多爾" />
      <Connection name="贊格拉，塔拉多爾" />
      <Connection name="救贖高崗，塔拉多爾" />
      <Connection name="泰洛卡避難所，塔拉多爾" />
      <Connection name="烏鴉鉤，阿拉卡山" />
      <Connection name="維爾泰洛克，阿拉卡山" />
      <Connection name="南埠，阿拉卡山" />
      <Connection name="急嘯零件廠，阿拉卡山" />
      <Connection name="頂尖挖掘場，阿拉卡山" />
      <Connection name="泰拉蕊哨站，納葛蘭" />
      <Connection name="試煉競技場，納葛蘭" />
    </Connections>
  </Node>
  <Node name="高地之路，格古隆德" continent="1116" master="81074" x="6352.58" y="746.234" z="116.163">
    <Connections>
      <Connection name="安伯瑞村，影月谷" />
      <Connection name="暮光林地，影月谷" />
      <Connection name="暴風之盾 (聯盟)，艾斯蘭" />
      <Connection name="達克瑞姆，影月谷" />
      <Connection name="埃羅多爾 (聯盟)，影月谷" />
      <Connection name="落月之地 (聯盟)，影月谷" />
      <Connection name="荒林小徑，格古隆德" />
      <Connection name="烏瑞恩堡 (聯盟)，塔拉多爾" />
      <Connection name="贊格拉，塔拉多爾" />
      <Connection name="救贖高崗，塔拉多爾" />
      <Connection name="泰洛卡避難所，塔拉多爾" />
      <Connection name="烏鴉鉤，阿拉卡山" />
      <Connection name="維爾泰洛克，阿拉卡山" />
      <Connection name="南埠，阿拉卡山" />
      <Connection name="急嘯零件廠，阿拉卡山" />
      <Connection name="頂尖挖掘場，阿拉卡山" />
      <Connection name="泰拉蕊哨站，納葛蘭" />
      <Connection name="試煉競技場，納葛蘭" />
    </Connections>
  </Node>
  <Node name="深根林，格古隆德" continent="1116" x="5412.85" y="1271.05" z="101.89">
    <Connections />
  </Node>
  <Node name="鋼鐵碼頭，格古隆德" continent="1116" x="8486.15" y="1544.24" z="78.8754">
    <Connections />
  </Node>
  <Node name="鋼鐵軍火廠，霜火峰" continent="1116" x="5724.26" y="2163.64" z="157.575">
    <Connections />
  </Node>
  <Node name="暗潮棲息地，影月谷" continent="1116" x="-974.125" y="-1739.3" z="2.99791">
    <Connections />
  </Node>
  <Node name="天海山脊，格古隆德" continent="1116" x="7596.2" y="1829.05" z="79.0772">
    <Connections />
  </Node>
  <Node name="靜謐庭院，影月谷" continent="1116" x="407.042" y="-2449.73" z="99.2637">
    <Connections />
  </Node>
  <Node name="卡拉伯爾神廟，影月谷" continent="1116" x="405.788" y="-2448.75" z="99.2643">
    <Connections />
  </Node>
  <Node name="永茂林野地，格古隆德" continent="1116" x="7093.6" y="404.74" z="112.001">
    <Connections />
  </Node>
  <Node name="亞吉塔的小屋，影月谷" continent="1116" x="676.424" y="701.439" z="113.96">
    <Connections />
  </Node>
  <Node name="里茲特的營地，納葛蘭" continent="1116" x="3761.26" y="6430.15" z="21.6669">
    <Connections />
  </Node>
  <Node name="尼維克的瞰臺，納葛蘭" continent="1116" x="2053.66" y="6507.39" z="32.264">
    <Connections />
  </Node>
  <Node name="喬茲的萊拉克，納葛蘭" continent="1116" x="3676.04" y="5776.19" z="45.4013">
    <Connections />
  </Node>
  <Node name="永茂林瞰臺，格古隆德" continent="1116" x="8018.09" y="-560.49" z="154.967">
    <Connections />
  </Node>
  <Node name="阿克塔崗哨，塔南森林" continent="1116" x="4569.44" y="335.054" z="221.197">
    <Connections />
  </Node>
  <Node name="鋼鐵前線，塔南森林" continent="1116" x="4074.97" y="1183.75" z="160.928">
    <Connections />
  </Node>
  <Node name="大地穹殿，塔南森林" continent="1116" x="3475.28" y="-762.552" z="41.3906">
    <Connections />
  </Node>
  <Node name="馬洛守望，塔南森林" continent="1116" x="4457.54" y="-574.693" z="49.3765">
    <Connections />
  </Node>
  <Node name="夏納瑞營地，塔南森林" continent="1116" x="3728.38" y="157.931" z="56.1153">
    <Connections />
  </Node>
  <Node name="破源者之冠，格古隆德" continent="1116" x="6593.43" y="1316.04" z="64.6343">
    <Connections />
  </Node>
</FlightNodes>